Hafsa/Hafsa.py
Hafsa/__init__.py
hafsa-1.0.5.dist-info/METADATA
hafsa-1.0.5.dist-info/WHEEL
hafsa-1.0.5.dist-info/top_level.txt
hafsa-1.0.5.dist-info/RECORD
